anatomy/__init__.py
anatomy/_algorithm.py
anatomy/_base.py
anatomy/_mas.py
anatomy/_models.py
anatomy/_subsets.py
anatomy-0.1.6.dist-info/LICENSE
anatomy-0.1.6.dist-info/METADATA
anatomy-0.1.6.dist-info/WHEEL
anatomy-0.1.6.dist-info/top_level.txt
anatomy-0.1.6.dist-info/RECORD
