Metadata-Version: 2.1
Name: anatomy
Version: 0.1.6
Summary: Shapley-based decomposition to anatomize the of out-of-sample accuracy of time-series forecasting models
Home-page: https://github.com/sander-sn/anatomy
Author: Sander Schwenk-Nebbe
Author-email: sandersn@econ.au.dk
License: MIT
Requires-Python: >=3.9
License-File: LICENSE
Requires-Dist: joblib >=0.15.0
Requires-Dist: numpy >=1.18.1
Requires-Dist: pandas >=1.0.0
